marketplace/__init__.py
marketplace/client.py
marketplace/version.py
marketplace/app/__init__.py
marketplace/app/utils.py
marketplace/app/v0/__init__.py
marketplace/app/v0/base.py
marketplace/app/v0/object_storage.py
marketplace/app/v0/transformation.py
marketplace/app/v0/utils.py
marketplace/datasink_client/__init__.py
marketplace/datasink_client/cli.py
marketplace/datasink_client/session.py
marketplace/datasink_client/utils.py
marketplace/message_broker/__init__.py
marketplace/message_broker/rpc_server.py
marketplace/message_broker/utils.py
marketplace_sdk-0.5.0.dist-info/LICENSE
marketplace_sdk-0.5.0.dist-info/METADATA
marketplace_sdk-0.5.0.dist-info/WHEEL
marketplace_sdk-0.5.0.dist-info/entry_points.txt
marketplace_sdk-0.5.0.dist-info/top_level.txt
marketplace_sdk-0.5.0.dist-info/RECORD
