Metadata-Version: 2.1
Name: marketplace-sdk
Version: 0.5.0
Summary: Software Development Toolkit to communicate with the Materials MarketPlace platform.
Home-page: https://github.com/materials-marketplace/python-sdk
Author: Carl Simon Adorf, Pablo de Andres, Pranjali Singh and the AiiDAlab team
Author-email: simon.adorf@epfl.ch, pablo.de.andres@iwm.fraunhofer.de, pranjali.singh@iwm.fraunhofer.de
License: MIT
Classifier: Development Status :: 2 - Pre-Alpha
Classifier: License :: OSI Approved :: MIT License
Classifier: Programming Language :: Python :: 3
Classifier: Programming Language :: Python :: 3 :: Only
Classifier: Programming Language :: Python :: Implementation :: CPython
Requires-Python: >=3.8
License-File: LICENSE
Requires-Dist: fastapi (<=0.95.1,>0.75)
Requires-Dist: marketplace-standard-app-api (~=0.4)
Requires-Dist: packaging (<=23.0,>=21.3)
Requires-Dist: pika (~=1.2)
Requires-Dist: python-keycloak (==2.12.0)
Requires-Dist: rdflib (==6.2.0)
Requires-Dist: rdflib-jsonld (==0.6.2)
Requires-Dist: requests (<3.0,>2.26.0)
Provides-Extra: dev
Requires-Dist: bumpver (==2021.1114) ; extra == 'dev'
Requires-Dist: dunamai (==1.7.0) ; extra == 'dev'
Provides-Extra: pre_commit
Requires-Dist: pre-commit (==2.15.0) ; extra == 'pre_commit'
Provides-Extra: tests
Requires-Dist: pytest (==6.2.5) ; extra == 'tests'
Requires-Dist: requests-mock (==1.9.3) ; extra == 'tests'
